rtl_works/2022340107026杨果林期末作业/LIF_neuron.v
module LIF_neuron (
    input wire clk,
    input wire reset,
    input wire x1,
    input wire x2,
    input wire [31:0] s1,
    input wire [31:0] s2,
    input wire [31:0] alpha,
    output reg spike
);

    reg signed[31:0] membrane_potential;

    always @(posedge clk or posedge reset) begin
        if (reset) begin
            membrane_potential <= 32'sd0;
            spike <= 1'b0;
        end else begin
            // 更新膜电位
            membrane_potential <= membrane_potential + (x1 ? s1 : 32'd0) + (x2 ? s2 : 32'd0) - alpha;

            // 检查是否产生脉冲
            if (membrane_potential >= 32'sd1) begin
                spike <= 1'b1;
                membrane_potential <= 32'sd0; // 重置膜电位
            end else begin
                spike <= 1'b0;
            end
        end
    end

endmodule

rtl_works/2022340107026杨果林期末作业/waveform.vcd
$version Generated by VerilatedVcd $end
$timescale 1ps $end

 $scope module TOP $end
  $var wire 32 ) alpha [31:0] $end
  $var wire  1 # clk $end
  $var wire  1 $ reset $end
  $var wire 32 ' s1 [31:0] $end
  $var wire 32 ( s2 [31:0] $end
  $var wire  1 * spike $end
  $var wire  1 % x1 $end
  $var wire  1 & x2 $end
  $scope module LIF_neuron $end
   $var wire 32 ) alpha [31:0] $end
   $var wire  1 # clk $end
   $var wire 32 + membrane_potential [31:0] $end
   $var wire  1 $ reset $end
   $var wire 32 ' s1 [31:0] $end
   $var wire 32 ( s2 [31:0] $end
   $var wire  1 * spike $end
   $var wire  1 % x1 $end
   $var wire  1 & x2 $end
  $upscope $end
 $upscope $end
$enddefinitions $end


#0
1#
1$
1%
1&
b00000000000000000000000000000001 '
b00000000000000000000000000000001 (
b00000000000000000000000000000001 )
0*
b00000000000000000000000000000000 +
#5
0#
#10
1#
0%
0&
#15
0#
#20
1#
1%
1&
#25
0#
#30
1#
0%
0&
#35
0#
#40
1#
1%
1&
#45
0#
#50
1#
0%
0&
#55
0#
#60
1#
1%
1&
#65
0#
#70
1#
0%
0&
#75
0#
#80
1#
1%
1&
#85
0#
#90
1#
0%
0&
#95
0#
#100
1#
0$
1%
1&
b00000000000000000000000000000001 +
#105
0#
#110
1#
0%
0&
1*
b00000000000000000000000000000000 +
#115
0#
#120
1#
1%
1&
0*
b00000000000000000000000000000001 +
#125
0#
#130
1#
0%
0&
1*
b00000000000000000000000000000000 +
#135
0#
#140
1#
1%
1&
0*
b00000000000000000000000000000001 +
#145
0#
#150
1#
0%
0&
1*
b00000000000000000000000000000000 +
#155
0#
#160
1#
1%
1&
0*
b00000000000000000000000000000001 +
#165
0#
#170
1#
0%
0&
1*
b00000000000000000000000000000000 +
#175
0#
#180
1#
1%
1&
0*
b00000000000000000000000000000001 +
#185
0#
#190
1#
0%
0&
1*
b00000000000000000000000000000000 +
#195
0#
#200
1#
1%
1&
0*
b00000000000000000000000000000001 +
#205
0#
#210
1#
0%
0&
1*
b00000000000000000000000000000000 +
#215
0#
#220
1#
1%
1&
0*
b00000000000000000000000000000001 +
#225
0#
#230
1#
0%
0&
1*
b00000000000000000000000000000000 +
#235
0#
#240
1#
1%
1&
0*
b00000000000000000000000000000001 +
#245
0#
#250
1#
0%
0&
1*
b00000000000000000000000000000000 +
#255
0#
#260
1#
1%
1&
0*
b00000000000000000000000000000001 +
#265
0#
#270
1#
0%
0&
1*
b00000000000000000000000000000000 +
#275
0#
#280
1#
1%
1&
0*
b00000000000000000000000000000001 +
#285
0#
#290
1#
0%
0&
1*
b00000000000000000000000000000000 +
#295
0#
#300
1#
1%
1&
0*
b00000000000000000000000000000001 +
#305
0#
#310
1#
0%
0&
1*
b00000000000000000000000000000000 +
#315
0#
#320
1#
1%
1&
0*
b00000000000000000000000000000001 +
#325
0#
#330
1#
0%
0&
1*
b00000000000000000000000000000000 +
#335
0#
#340
1#
1%
1&
0*
b00000000000000000000000000000001 +
#345
0#
#350
1#
0%
0&
1*
b00000000000000000000000000000000 +
#355
0#
#360
1#
1%
1&
0*
b00000000000000000000000000000001 +
#365
0#
#370
1#
0%
0&
1*
b00000000000000000000000000000000 +
#375
0#
#380
1#
1%
1&
0*
b00000000000000000000000000000001 +
#385
0#
#390
1#
0%
0&
1*
b00000000000000000000000000000000 +
#395
0#
#400
1#
1%
1&
0*
b00000000000000000000000000000001 +
#405
0#
#410
1#
0%
0&
1*
b00000000000000000000000000000000 +
#415
0#
#420
1#
1%
1&
0*
b00000000000000000000000000000001 +
#425
0#
#430
1#
0%
0&
1*
b00000000000000000000000000000000 +
#435
0#
#440
1#
1%
1&
0*
b00000000000000000000000000000001 +
#445
0#
#450
1#
0%
0&
1*
b00000000000000000000000000000000 +
#455
0#
#460
1#
1%
1&
0*
b00000000000000000000000000000001 +
#465
0#
#470
1#
0%
0&
1*
b00000000000000000000000000000000 +
#475
0#
#480
1#
1%
1&
0*
b00000000000000000000000000000001 +
#485
0#
#490
1#
0%
0&
1*
b00000000000000000000000000000000 +
#495
0#
#500
1#
1%
1&
0*
b00000000000000000000000000000001 +
#505
0#
#510
1#
0%
0&
1*
b00000000000000000000000000000000 +
#515
0#
#520
1#
1%
1&
0*
b00000000000000000000000000000001 +
#525
0#
#530
1#
0%
0&
1*
b00000000000000000000000000000000 +
#535
0#
#540
1#
1%
1&
0*
b00000000000000000000000000000001 +
#545
0#
#550
1#
0%
0&
1*
b00000000000000000000000000000000 +
#555
0#
#560
1#
1%
1&
0*
b00000000000000000000000000000001 +
#565
0#
#570
1#
0%
0&
1*
b00000000000000000000000000000000 +
#575
0#
#580
1#
1%
1&
0*
b00000000000000000000000000000001 +
#585
0#
#590
1#
0%
0&
1*
b00000000000000000000000000000000 +
#595
0#
#600
1#
1%
1&
0*
b00000000000000000000000000000001 +
#605
0#
#610
1#
0%
0&
1*
b00000000000000000000000000000000 +
#615
0#
#620
1#
1%
1&
0*
b00000000000000000000000000000001 +
#625
0#
#630
1#
0%
0&
1*
b00000000000000000000000000000000 +
#635
0#
#640
1#
1%
1&
0*
b00000000000000000000000000000001 +
#645
0#
#650
1#
0%
0&
1*
b00000000000000000000000000000000 +
#655
0#
#660
1#
1%
1&
0*
b00000000000000000000000000000001 +
#665
0#
#670
1#
0%
0&
1*
b00000000000000000000000000000000 +
#675
0#
#680
1#
1%
1&
0*
b00000000000000000000000000000001 +
#685
0#
#690
1#
0%
0&
1*
b00000000000000000000000000000000 +
#695
0#
#700
1#
1%
1&
0*
b00000000000000000000000000000001 +
#705
0#
#710
1#
0%
0&
1*
b00000000000000000000000000000000 +
#715
0#
#720
1#
1%
1&
0*
b00000000000000000000000000000001 +
#725
0#
#730
1#
0%
0&
1*
b00000000000000000000000000000000 +
#735
0#
#740
1#
1%
1&
0*
b00000000000000000000000000000001 +
#745
0#
#750
1#
0%
0&
1*
b00000000000000000000000000000000 +
#755
0#
#760
1#
1%
1&
0*
b00000000000000000000000000000001 +
#765
0#
#770
1#
0%
0&
1*
b00000000000000000000000000000000 +
#775
0#
#780
1#
1%
1&
0*
b00000000000000000000000000000001 +
#785
0#
#790
1#
0%
0&
1*
b00000000000000000000000000000000 +
#795
0#
#800
1#
1%
1&
0*
b00000000000000000000000000000001 +
#805
0#
#810
1#
0%
0&
1*
b00000000000000000000000000000000 +
#815
0#
#820
1#
1%
1&
0*
b00000000000000000000000000000001 +
#825
0#
#830
1#
0%
0&
1*
b00000000000000000000000000000000 +
#835
0#
#840
1#
1%
1&
0*
b00000000000000000000000000000001 +
#845
0#
#850
1#
0%
0&
1*
b00000000000000000000000000000000 +
#855
0#
#860
1#
1%
1&
0*
b00000000000000000000000000000001 +
#865
0#
#870
1#
0%
0&
1*
b00000000000000000000000000000000 +
#875
0#
#880
1#
1%
1&
0*
b00000000000000000000000000000001 +
#885
0#
#890
1#
0%
0&
1*
b00000000000000000000000000000000 +
#895
0#
#900
1#
1%
1&
0*
b00000000000000000000000000000001 +
#905
0#
#910
1#
0%
0&
1*
b00000000000000000000000000000000 +
#915
0#
#920
1#
1%
1&
0*
b00000000000000000000000000000001 +
#925
0#
#930
1#
0%
0&
1*
b00000000000000000000000000000000 +
#935
0#
#940
1#
1%
1&
0*
b00000000000000000000000000000001 +
#945
0#
#950
1#
0%
0&
1*
b00000000000000000000000000000000 +
#955
0#
#960
1#
1%
1&
0*
b00000000000000000000000000000001 +
#965
0#
#970
1#
0%
0&
1*
b00000000000000000000000000000000 +
#975
0#
#980
1#
1%
1&
0*
b00000000000000000000000000000001 +
#985
0#
#990
1#
0%
0&
1*
b00000000000000000000000000000000 +
#995
0#
#1000
1#
1%
1&
0*
b00000000000000000000000000000001 +
#1005
0#
#1010
1#
0%
0&
1*
b00000000000000000000000000000000 +
#1015
0#
#1020
1#
1%
1&
0*
b00000000000000000000000000000001 +
#1025
0#
#1030
1#
0%
0&
1*
b00000000000000000000000000000000 +
#1035
0#
#1040
1#
1%
1&
0*
b00000000000000000000000000000001 +
#1045
0#
#1050
1#
0%
0&
1*
b00000000000000000000000000000000 +
#1055
0#
#1060
1#
1%
1&
0*
b00000000000000000000000000000001 +
#1065
0#
#1070
1#
0%
0&
1*
b00000000000000000000000000000000 +
#1075
0#
#1080
1#
1%
1&
0*
b00000000000000000000000000000001 +
#1085
0#
#1090
1#
0%
0&
1*
b00000000000000000000000000000000 +
#1095
0#
#1100
1#
1%
1&
0*
b00000000000000000000000000000001 +
#1105
0#
#1110
1#
0%
0&
1*
b00000000000000000000000000000000 +
#1115
0#
#1120
1#
1%
1&
0*
b00000000000000000000000000000001 +
#1125
0#
#1130
1#
0%
0&
1*
b00000000000000000000000000000000 +
#1135
0#
#1140
1#
1%
1&
0*
b00000000000000000000000000000001 +
#1145
0#
#1150
1#
0%
0&
1*
b00000000000000000000000000000000 +
#1155
0#
#1160
1#
1%
1&
0*
b00000000000000000000000000000001 +
#1165
0#
#1170
1#
0%
0&
1*
b00000000000000000000000000000000 +
#1175
0#
#1180
1#
1%
1&
0*
b00000000000000000000000000000001 +
#1185
0#
#1190
1#
0%
0&
1*
b00000000000000000000000000000000 +
#1195
0#
#1200
1#
1%
1&
0*
b00000000000000000000000000000001 +
#1205
0#
#1210
1#
0%
0&
1*
b00000000000000000000000000000000 +
#1215
0#
#1220
1#
1%
1&
0*
b00000000000000000000000000000001 +
#1225
0#
#1230
1#
0%
0&
1*
b00000000000000000000000000000000 +
#1235
0#
#1240
1#
1%
1&
0*
b00000000000000000000000000000001 +
#1245
0#
#1250
1#
0%
0&
1*
b00000000000000000000000000000000 +
#1255
0#
#1260
1#
1%
1&
0*
b00000000000000000000000000000001 +
#1265
0#
#1270
1#
0%
0&
1*
b00000000000000000000000000000000 +
#1275
0#
#1280
1#
1%
1&
0*
b00000000000000000000000000000001 +
#1285
0#
#1290
1#
0%
0&
1*
b00000000000000000000000000000000 +
#1295
0#
#1300
1#
1%
1&
0*
b00000000000000000000000000000001 +
#1305
0#
#1310
1#
0%
0&
1*
b00000000000000000000000000000000 +
#1315
0#
#1320
1#
1%
1&
0*
b00000000000000000000000000000001 +
#1325
0#
#1330
1#
0%
0&
1*
b00000000000000000000000000000000 +
#1335
0#
#1340
1#
1%
1&
0*
b00000000000000000000000000000001 +
#1345
0#
#1350
1#
0%
0&
1*
b00000000000000000000000000000000 +
#1355
0#
#1360
1#
1%
1&
0*
b00000000000000000000000000000001 +
#1365
0#
#1370
1#
0%
0&
1*
b00000000000000000000000000000000 +
#1375
0#
#1380
1#
1%
1&
0*
b00000000000000000000000000000001 +
#1385
0#
#1390
1#
0%
0&
1*
b00000000000000000000000000000000 +
#1395
0#
#1400
1#
1%
1&
0*
b00000000000000000000000000000001 +
#1405
0#
#1410
1#
0%
0&
1*
b00000000000000000000000000000000 +
#1415
0#
#1420
1#
1%
1&
0*
b00000000000000000000000000000001 +
#1425
0#
#1430
1#
0%
0&
1*
b00000000000000000000000000000000 +
#1435
0#
#1440
1#
1%
1&
0*
b00000000000000000000000000000001 +
#1445
0#
#1450
1#
0%
0&
1*
b00000000000000000000000000000000 +
#1455
0#
#1460
1#
1%
1&
0*
b00000000000000000000000000000001 +
#1465
0#
#1470
1#
0%
0&
1*
b00000000000000000000000000000000 +
#1475
0#
#1480
1#
1%
1&
0*
b00000000000000000000000000000001 +
#1485
0#
#1490
1#
0%
0&
1*
b00000000000000000000000000000000 +
#1495
0#
#1500
1#
1%
1&
0*
b00000000000000000000000000000001 +
#1505
0#
#1510
1#
0%
0&
1*
b00000000000000000000000000000000 +
#1515
0#
#1520
1#
1%
1&
0*
b00000000000000000000000000000001 +
#1525
0#
#1530
1#
0%
0&
1*
b00000000000000000000000000000000 +
#1535
0#
#1540
1#
1%
1&
0*
b00000000000000000000000000000001 +
#1545
0#
#1550
1#
0%
0&
1*
b00000000000000000000000000000000 +
#1555
0#
#1560
1#
1%
1&
0*
b00000000000000000000000000000001 +
#1565
0#
#1570
1#
0%
0&
1*
b00000000000000000000000000000000 +
#1575
0#
#1580
1#
1%
1&
0*
b00000000000000000000000000000001 +
#1585
0#
#1590
1#
0%
0&
1*
b00000000000000000000000000000000 +
#1595
0#
#1600
1#
1%
1&
0*
b00000000000000000000000000000001 +
#1605
0#
#1610
1#
0%
0&
1*
b00000000000000000000000000000000 +
#1615
0#
#1620
1#
1%
1&
0*
b00000000000000000000000000000001 +
#1625
0#
#1630
1#
0%
0&
1*
b00000000000000000000000000000000 +
#1635
0#
#1640
1#
1%
1&
0*
b00000000000000000000000000000001 +
#1645
0#
#1650
1#
0%
0&
1*
b00000000000000000000000000000000 +
#1655
0#
#1660
1#
1%
1&
0*
b00000000000000000000000000000001 +
#1665
0#
#1670
1#
0%
0&
1*
b00000000000000000000000000000000 +
#1675
0#
#1680
1#
1%
1&
0*
b00000000000000000000000000000001 +
#1685
0#
#1690
1#
0%
0&
1*
b00000000000000000000000000000000 +
#1695
0#
#1700
1#
1%
1&
0*
b00000000000000000000000000000001 +
#1705
0#
#1710
1#
0%
0&
1*
b00000000000000000000000000000000 +
#1715
0#
#1720
1#
1%
1&
0*
b00000000000000000000000000000001 +
#1725
0#
#1730
1#
0%
0&
1*
b00000000000000000000000000000000 +
#1735
0#
#1740
1#
1%
1&
0*
b00000000000000000000000000000001 +
#1745
0#
#1750
1#
0%
0&
1*
b00000000000000000000000000000000 +
#1755
0#
#1760
1#
1%
1&
0*
b00000000000000000000000000000001 +
#1765
0#
#1770
1#
0%
0&
1*
b00000000000000000000000000000000 +
#1775
0#
#1780
1#
1%
1&
0*
b00000000000000000000000000000001 +
#1785
0#
#1790
1#
0%
0&
1*
b00000000000000000000000000000000 +
#1795
0#
#1800
1#
1%
1&
0*
b00000000000000000000000000000001 +
#1805
0#
#1810
1#
0%
0&
1*
b00000000000000000000000000000000 +
#1815
0#
#1820
1#
1%
1&
0*
b00000000000000000000000000000001 +
#1825
0#
#1830
1#
0%
0&
1*
b00000000000000000000000000000000 +
#1835
0#
#1840
1#
1%
1&
0*
b00000000000000000000000000000001 +
#1845
0#
#1850
1#
0%
0&
1*
b00000000000000000000000000000000 +
#1855
0#
#1860
1#
1%
1&
0*
b00000000000000000000000000000001 +
#1865
0#
#1870
1#
0%
0&
1*
b00000000000000000000000000000000 +
#1875
0#
#1880
1#
1%
1&
0*
b00000000000000000000000000000001 +
#1885
0#
#1890
1#
0%
0&
1*
b00000000000000000000000000000000 +
#1895
0#
#1900
1#
1%
1&
0*
b00000000000000000000000000000001 +
#1905
0#
#1910
1#
0%
0&
1*
b00000000000000000000000000000000 +
#1915
0#
#1920
1#
1%
1&
0*
b00000000000000000000000000000001 +
#1925
0#
#1930
1#
0%
0&
1*
b00000000000000000000000000000000 +
#1935
0#
#1940
1#
1%
1&
0*
b00000000000000000000000000000001 +
#1945
0#
#1950
1#
0%
0&
1*
b00000000000000000000000000000000 +
#1955
0#
#1960
1#
1%
1&
0*
b00000000000000000000000000000001 +
#1965
0#
#1970
1#
0%
0&
1*
b00000000000000000000000000000000 +
#1975
0#
#1980
1#
1%
1&
0*
b00000000000000000000000000000001 +
#1985
0#
#1990
1#
0%
0&
1*
b00000000000000000000000000000000 +
